marisa_trie.cpython-313-darwin.so
marisa_trie-1.3.0.dist-info/RECORD
marisa_trie-1.3.0.dist-info/WHEEL
marisa_trie-1.3.0.dist-info/top_level.txt
marisa_trie-1.3.0.dist-info/METADATA
marisa_trie-1.3.0.dist-info/licenses/LICENSE
marisa_trie-1.3.0.dist-info/licenses/AUTHORS.rst
marisa_trie-1.3.0.dist-info/licenses/marisa-trie/AUTHORS
marisa_trie-1.3.0.dist-info/licenses/marisa-trie/COPYING.md
