Metadata-Version: 2.4
Name: marisa-trie
Version: 1.3.0
Summary: Static memory-efficient and fast Trie-like structures for Python.
Author-email: Mikhail Korobov <kmike84@gmail.com>
License-Expression: MIT AND (BSD-2-Clause OR LGPL-2.1-or-later)
Project-URL: Source, https://github.com/pytries/marisa-trie
Classifier: Development Status :: 4 - Beta
Classifier: Intended Audience :: Developers
Classifier: Intended Audience :: Science/Research
Classifier: Programming Language :: Cython
Classifier: Programming Language :: Python
Classifier: Programming Language :: Python :: 3
Classifier: Programming Language :: Python :: 3.9
Classifier: Programming Language :: Python :: 3.10
Classifier: Programming Language :: Python :: 3.11
Classifier: Programming Language :: Python :: 3.12
Classifier: Programming Language :: Python :: 3.13
Classifier: Programming Language :: Python :: 3.14
Classifier: Programming Language :: Python :: Implementation :: CPython
Classifier: Topic :: Software Development :: Libraries :: Python Modules
Classifier: Topic :: Scientific/Engineering :: Information Analysis
Classifier: Topic :: Text Processing :: Linguistic
Requires-Python: >=3.9
License-File: AUTHORS.rst
License-File: LICENSE
License-File: marisa-trie/AUTHORS
License-File: marisa-trie/COPYING.md
Provides-Extra: test
Requires-Dist: hypothesis; extra == "test"
Requires-Dist: pytest; extra == "test"
Requires-Dist: readme_renderer; extra == "test"
Dynamic: license-file
